cognite/jupyterlitepatch/__init__.py
patch-sdk-jupyterlite/__init__.py
patch_sdk_jupyterlite-0.0.15.dist-info/METADATA
patch_sdk_jupyterlite-0.0.15.dist-info/WHEEL
patch_sdk_jupyterlite-0.0.15.dist-info/top_level.txt
patch_sdk_jupyterlite-0.0.15.dist-info/RECORD
