Metadata-Version: 2.1
Name: patch-sdk-jupyterlite
Version: 0.0.15
Summary: A patch for the Cognite SDK so it works in Jupyterlite
Home-page: UNKNOWN
Author: Anders Hafreager
Author-email: anders.hafreager@cognite.com
License: UNKNOWN
Platform: UNKNOWN
Requires-Python: >=3.5
